dc_etexter/__init__.py
dc_etexter/etexter.py
dc_etexter-0.1.2.dist-info/LICENSE.txt
dc_etexter-0.1.2.dist-info/METADATA
dc_etexter-0.1.2.dist-info/WHEEL
dc_etexter-0.1.2.dist-info/top_level.txt
dc_etexter-0.1.2.dist-info/RECORD
