Metadata-Version: 2.2
Name: dc_etexter
Version: 0.1.2
Summary: A simple SMS texter utility for Python projects
Author-email: Denise Case <denisecase@gmail.com>
License: MIT License
Project-URL: Homepage, https://github.com/denisecase/text-alert
Project-URL: Repository, https://github.com/denisecase/text-alert
Project-URL: BugTracker, https://github.com/denisecase/text-alert/issues
Keywords: sms,text,alert,notification
Classifier: Intended Audience :: Developers
Classifier: License :: OSI Approved :: MIT License
Classifier: Programming Language :: Python :: 3.11
Classifier: Programming Language :: Python :: 3.12
Requires-Python: >=3.11
License-File: LICENSE.txt
Provides-Extra: dev
Requires-Dist: pytest; extra == "dev"
Requires-Dist: twine; extra == "dev"
Requires-Dist: build; extra == "dev"
